parameterized_testcase
