Metadata-Version: 1.0
Name: parameterized-testcase
Version: 0.3
Summary: Create unittest-compatible parameterized testcases.
Home-page: http://code.google.com/p/parameterized-testcase/
Author: Austin Bingham
Author-email: austin.bingham@gmail.com
License: MIT
Keywords: unittest
Platform: any
Classifier: Development Status :: 4 - Beta
Classifier: Environment :: Console
Classifier: Intended Audience :: Developers
Classifier: License :: OSI Approved :: MIT License
Classifier: Operating System :: OS Independent
Classifier: Programming Language :: Python
Classifier: Topic :: Software Development :: Testing
